datacull/__init__.py
datacull/data.py
datacull/importance.py
datacull/logger.py
datacull/methods/CCS.py
datacull/methods/MetriQ.py
datacull/methods/RCAP.py
datacull/methods/RS2.py
datacull/methods/TDDS.py
datacull/methods/__init__.py
datacull-1.0.2.dist-info/METADATA
datacull-1.0.2.dist-info/WHEEL
datacull-1.0.2.dist-info/top_level.txt
datacull-1.0.2.dist-info/RECORD
