Metadata-Version: 2.4
Name: datacull
Version: 1.0.2
Summary: DataCull is a modular, light-weight data pruning library containing many dataset pruning (coreset selection) algorithm including the official Implementation of the paper, titled, RCAP: Robust, Class-Aware, Probab ilistic Dynamic Dataset Pruning
Home-page: https://github.com/atif-hassan/RCAP-dynamic-dataset-pruning
Author: Atif Hassan
Author-email: atif.hit.hassan@gmail.com
Requires-Dist: torch
Requires-Dist: tqdm
Requires-Dist: numpy
Requires-Dist: orjsonl
Dynamic: author
Dynamic: author-email
Dynamic: description
Dynamic: description-content-type
Dynamic: home-page
Dynamic: requires-dist
Dynamic: summary
